AUTHORS
CHANGELOG.rst
LICENSE
MANIFEST.in
README
README.rst
requirements.txt
setup.cfg
setup.py
docs/CHANGELOG.rst
docs/CONTRIBUTING.rst
docs/LICENSE.rst
docs/README.rst
docs/conf.py
docs/index.rst
docs/html/index.html
shift_divmod/__init__.py
shift_divmod/__main__.py
shift_divmod/template.py
shift_divmod.egg-info/PKG-INFO
shift_divmod.egg-info/SOURCES.txt
shift_divmod.egg-info/dependency_links.txt
shift_divmod.egg-info/not-zip-safe
shift_divmod.egg-info/top_level.txt
tests/__init__.py
tests/test_divmod.py
tests/test_sanity.py