Metadata-Version: 1.1
Name: shift-divmod
Version: 0.4.3
Summary: Implement faster divmod() for moduli with trailing 0 bits
Home-page: https://github.com/shlomif/shift_divmod
Author: Shlomi Fish
Author-email: shlomif@cpan.org
License: 3-clause BSD
Keywords: shift_divmod
Platform: any
Classifier: Development Status :: 1 - Planning
Classifier: Programming Language :: Python
Classifier: Programming Language :: Python :: 3
Classifier: Programming Language :: Python :: 3.5
Classifier: Programming Language :: Python :: 3.6
Classifier: Programming Language :: Python :: 3.7
Classifier: Programming Language :: Python :: 3.8
